setup.py
OffDownloader/__init__.py
OffDownloader/downloader.py
Offdownloader.egg-info/PKG-INFO
Offdownloader.egg-info/SOURCES.txt
Offdownloader.egg-info/dependency_links.txt
Offdownloader.egg-info/not-zip-safe
Offdownloader.egg-info/requires.txt
Offdownloader.egg-info/top_level.txt
bin/offdownloader