Metadata-Version: 1.1
Name: Offdownloader
Version: 1.0.2
Summary: Downloads Documentation from ReadTheDocs in multiple formats
Home-page: https://github.com/gkdeveloper/Off-documention
Author: Gaurav Kumar Verma
Author-email: gkverma1094@gmail.com
License: MIT
Platform: UNKNOWN
Classifier: Development Status :: 4 - Beta
Classifier: Topic :: Utilities
Classifier: Operating System :: OS Independent
Classifier: Programming Language :: Python
